{"_path":"/","_dir":"","_draft":false,"_partial":false,"_locale":"","title":"","description":"","layout":"wide","body":{"type":"root","children":[{"type":"element","tag":"div","props":{"align":"center"},"children":[{"type":"element","tag":"h1","props":{"id":"energy-storage-solutions-directory"},"children":[{"type":"text","value":"Energy Storage Solutions Directory"}]},{"type":"element","tag":"p","props":{},"children":[{"type":"text","value":"Browse companies that offer Battery Energy Storage Solution (BESS).  From flexible plug-and-play systems to utility-scale solutions, we've analyzed the options to make it easy for you to find the partner that will meet your needs."}]}]},{"type":"element","tag":"search","props":{},"children":[]},{"type":"element","tag":"directory-grid","props":{},"children":[]}],"toc":{"title":"","searchDepth":2,"depth":2,"links":[]}},"_type":"markdown","_id":"content:index.md","_source":"content","_file":"index.md","_stem":"index","_extension":"md","sitemap":{"loc":"/"}}