{"id":"f7d502a2-57ef-4213-8fc2-eadfe012f56a","timestamp":1735646239919,"matcher":{"static":{},"wildcard":{},"dynamic":{}},"prerendered":["/","/submit","/dir/power_sonic","/dir/power_storage_solutions","/dir/aggreko","/dir/ameresco","/dir/briggs__stratton","/dir/american_energy_storage_innovations_inc","/dir/ess_inc","/dir/csi_solar","/dir/concentric","/dir/energy_vault","/dir/fluence","/dir/energy_storage_solutions_llc","/dir/hero_future_energies","/dir/honeywell","/dir/owc","/dir/rwe","/dir/siemens_energy","/dir/sma_solar","/dir/stem","/dir/totalenergies","/dir/wartsila","/dir/total_energy_solutions","/advertise","/legal/privacy-policy"]}